Metadata-Version: 2.1
Name: odoo-addon-stock_analytic
Version: 18.0.1.1.0.6
Requires-Python: >=3.10
Requires-Dist: odoo==18.0.*
Summary: Adds analytic distribution in stock move
Home-page: https://github.com/OCA/account-analytic
License: AGPL-3
Author: Julius Network Solutions, ClearCorp, OpenSynergy Indonesia, Hibou Corp., Odoo Community Association (OCA)
Author-email: support@odoo-community.org
Classifier: Programming Language :: Python
Classifier: Framework :: Odoo
Classifier: Framework :: Odoo :: 18.0
Classifier: License :: OSI Approved :: GNU Affero General Public License v3
